{
    "id": 107576483,
    "name": "Two Dudes",
    "author": "Phantom",
    "creators": ["Phantom"],
    "verifier": "Phantom",
    "verification": "https://www.youtube.com/watch?v=MOFDaUJGudY",
    "percentToQualify": 100,
    "password": "Not Copyable",
    "records": [
        {
            "user": "RedIntention",
            "link": "https://www.youtube.com/watch?v=nLhY3okDCpo",
            "percent": 100,
            "hz": 120
        },
        {
    "user": "INSANEMELTON",
    "link": "https://www.youtube.com/watch?v=chzrJf9IqRE",
    "percent": 100,
    "hz": 60
        },
        {
            "user": "ShinnBoi",
            "link": "https://www.youtube.com/watch?v=J8RBElAaErQ",
            "percent": 100,
            "hz": 60
        },
        {            
        "user": "Danodash",
        "link": "https://www.youtube.com/watch?v=NLNP6aaV6O4",
        "percent": 100,
        "hz": 60
        },
        {
            "user": "Icetastic",
            "link": "https://drive.google.com/file/d/1hd4wPBGC39Off41Fyv3OMksZpZI38w-Q/view?usp=drivesdk",
            "percent": 100,
            "hz": 60
        }
    ]
    
}
